macrobond_api_constants/CalendarDateMode.py
macrobond_api_constants/CalendarMergeMode.py
macrobond_api_constants/MetadataValueType.py
macrobond_api_constants/SeriesFrequency.py
macrobond_api_constants/SeriesMissingValueMethod.py
macrobond_api_constants/SeriesPartialPeriodsMethod.py
macrobond_api_constants/SeriesToHigherFrequencyMethod.py
macrobond_api_constants/SeriesToLowerFrequencyMethod.py
macrobond_api_constants/SeriesWeekdays.py
macrobond_api_constants/__init__.py
macrobond_api_constants-1.0.2.dist-info/LICENSE
macrobond_api_constants-1.0.2.dist-info/METADATA
macrobond_api_constants-1.0.2.dist-info/WHEEL
macrobond_api_constants-1.0.2.dist-info/top_level.txt
macrobond_api_constants-1.0.2.dist-info/RECORD
