Metadata-Version: 2.1
Name: macrobond-api-constants
Version: 1.0.2
Summary: Package with constants used by Macrobond API
Home-page: https://www.macrobond.com
Author: Macrobond Financial
Author-email: support@macrobond.com
License: MIT
Platform: UNKNOWN
Classifier: Programming Language :: Python
Classifier: Operating System :: Microsoft :: Windows
Requires-Python: >=2.7
